[{"model": "files_api.file", "pk": 1, "fields": {"file": "files/Емельянов_Александр_Владимирович.pdf", "uploaded_at": "2024-02-04T15:54:04.992Z", "processed": false}}, {"model": "files_api.file", "pk": 2, "fields": {"file": "files/roadmap.docx", "uploaded_at": "2024-02-04T18:44:50.915Z", "processed": false}}, {"model": "files_api.file", "pk": 3, "fields": {"file": "files/roadmap_9sINmQv.docx", "uploaded_at": "2024-02-04T19:30:11.747Z", "processed": false}}, {"model": "files_api.file", "pk": 4, "fields": {"file": "files/roadmap_3wBR7o0.docx", "uploaded_at": "2024-02-06T11:06:33.315Z", "processed": true}}, {"model": "files_api.file", "pk": 5, "fields": {"file": "files/roadmap_tCKKRfL.docx", "uploaded_at": "2024-02-06T11:25:25.500Z", "processed": true}}, {"model": "files_api.file", "pk": 6, "fields": {"file": "files/roadmap_mAYUk02.docx", "uploaded_at": "2024-02-06T11:29:01.301Z", "processed": true}}, {"model": "files_api.file", "pk": 7, "fields": {"file": "files/roadmap_6awxCew.docx", "uploaded_at": "2024-02-06T11:29:20.629Z", "processed": true}}, {"model": "files_api.file", "pk": 8, "fields": {"file": "files/roadmap_qdmsZtr.docx", "uploaded_at": "2024-02-06T11:30:02.307Z", "processed": true}}, {"model": "files_api.file", "pk": 9, "fields": {"file": "files/roadmap_8D4os2N.docx", "uploaded_at": "2024-02-06T11:31:47.181Z", "processed": true}}, {"model": "files_api.file", "pk": 10, "fields": {"file": "files/roadmap_Emj6X5F.docx", "uploaded_at": "2024-02-06T11:51:56.178Z", "processed": true}}, {"model": "files_api.file", "pk": 11, "fields": {"file": "files/roadmap_RYh3Wlb.docx", "uploaded_at": "2024-02-06T11:52:38.566Z", "processed": true}}, {"model": "files_api.file", "pk": 12, "fields": {"file": "files/roadmap_brZAnOR.docx", "uploaded_at": "2024-02-06T12:02:07.633Z", "processed": true}}, {"model": "files_api.file", "pk": 13, "fields": {"file": "files/roadmap_lGK1mSr.docx", "uploaded_at": "2024-02-06T12:02:26.579Z", "processed": true}}, {"model": "files_api.file", "pk": 14, "fields": {"file": "files/roadmap_blNfgnF.docx", "uploaded_at": "2024-02-06T12:09:29.955Z", "processed": true}}, {"model": "files_api.file", "pk": 15, "fields": {"file": "files/roadmap_JQwDG41.docx", "uploaded_at": "2024-02-06T12:10:38.810Z", "processed": true}}]
